jdbc2/__init__.py
jdbc2/core.py
jdbc2/sqlalchemy_dialect.py
jdbc2-0.1.2.dist-info/licenses/LICENSE
jdbc2-0.1.2.dist-info/METADATA
jdbc2-0.1.2.dist-info/WHEEL
jdbc2-0.1.2.dist-info/entry_points.txt
jdbc2-0.1.2.dist-info/top_level.txt
jdbc2-0.1.2.dist-info/RECORD
