Metadata-Version: 2.4
Name: JDBC2
Version: 0.1.2
Summary: Minimal Python DB-API 2.0 over JDBC via JPype, with a lightweight SQLAlchemy dialect
Author: Euan D. Macinnes
License: MIT
Project-URL: Homepage, https://example.com/jdbc2
Project-URL: Repository, https://example.com/jdbc2.git
Keywords: jdbc,dbapi,sqlalchemy,jpype,database
Classifier: Development Status :: 3 - Alpha
Classifier: Intended Audience :: Developers
Classifier: License :: OSI Approved :: MIT License
Classifier: Programming Language :: Python
Classifier: Programming Language :: Python :: 3
Classifier: Programming Language :: Python :: 3 :: Only
Classifier: Programming Language :: Python :: 3.8
Classifier: Programming Language :: Python :: 3.9
Classifier: Programming Language :: Python :: 3.10
Classifier: Programming Language :: Python :: 3.11
Classifier: Programming Language :: Python :: 3.12
Classifier: Operating System :: OS Independent
Classifier: Topic :: Database
Requires-Python: >=3.8
License-File: LICENSE
Requires-Dist: JPype1>=1.3.0
Provides-Extra: sqlalchemy
Requires-Dist: SQLAlchemy>=1.4; extra == "sqlalchemy"
Dynamic: license-file
